clsx/__init__.py
clsx/__version__.py
clsx/py.typed
clsx/abc/__init__.py
clsx/abc/class_names/__init__.py
clsx/abc/class_names/class_name.py
clsx/abc/class_names/class_name_character_iterable.py
clsx/abc/class_names/class_name_character_stream.py
clsx/abc/class_names/class_name_iterable.py
clsx/abc/class_names/nested_class_name_character_iterable.py
clsx/abc/conditions/__init__.py
clsx/abc/conditions/bool_condition.py
clsx/abc/conditions/callable_condition.py
clsx/abc/conditions/condition.py
clsx/abc/expressions/__init__.py
clsx/abc/expressions/callable_expression.py
clsx/abc/expressions/conditional_expression_tuple.py
clsx/abc/expressions/dict_expression.py
clsx/abc/expressions/expression.py
clsx/abc/expressions/expression_iterable.py
clsx/abc/expressions/expression_list.py
clsx/abc/expressions/expression_set.py
clsx/abc/expressions/expression_tuple.py
clsx/abc/expressions/hashable_expression.py
clsx/abc/expressions/unhashable_expression.py
clsx/abc/expressions/variadic_expression_tuple.py
clsx/api/__init__.py
clsx/api/_clsx.py
clsx/api/_clsx_test.py
clsx/contrib/__init__.py
clsx/contrib/itertools/__init__.py
clsx/contrib/itertools/_dedup.py
clsx/contrib/itertools/_flatten_str.py
clsx/contrib/itertools/abc/__init__.py
clsx/contrib/itertools/abc/nested_str_iterable.py
clsx/contrib/stdlib/__init__.py
clsx/contrib/stdlib/representable_lambda.py
clsx/evaluation/__init__.py
clsx/evaluation/expression_evaluator.py
clsx/evaluation/expression_evaluator_test.py
clsx/parsing/__init__.py
clsx/parsing/class_name_parser.py
clsx-0.1.1.dist-info/METADATA
clsx-0.1.1.dist-info/WHEEL
clsx-0.1.1.dist-info/licenses/LICENSE
clsx-0.1.1.dist-info/RECORD
